LICENSE
MANIFEST.in
README.md
setup.py
bible/__init__.py
bible/bible.py
bible/data/kjv.jsonl
biblepy.egg-info/PKG-INFO
biblepy.egg-info/SOURCES.txt
biblepy.egg-info/dependency_links.txt
biblepy.egg-info/top_level.txt
tests/__init__.py
tests/bible_test.py